qo/__init__.py
qo/qo_utils.py
qo/tw.py
qo-0.0.20.dist-info/LICENSE
qo-0.0.20.dist-info/METADATA
qo-0.0.20.dist-info/WHEEL
qo-0.0.20.dist-info/top_level.txt
qo-0.0.20.dist-info/RECORD
