Metadata-Version: 2.1
Name: qo
Version: 0.0.20
Summary: Quick access to code favorites
Home-page: https://github.com/i2mint/qo
Author-email: thorwhalen1@gmail.com
License: mit
Platform: any
License-File: LICENSE
